jsonfield_validation/__init__.py
jsonfield_validation/validator.py
jsonfield_validation-0.3.0.dist-info/LICENSE.txt
jsonfield_validation-0.3.0.dist-info/METADATA
jsonfield_validation-0.3.0.dist-info/WHEEL
jsonfield_validation-0.3.0.dist-info/top_level.txt
jsonfield_validation-0.3.0.dist-info/RECORD
