Metadata-Version: 2.1
Name: jsonfield-validation
Version: 0.3.0
Summary: Validator class for Django model JSON fields.
Home-page: https://github.com/chrislawlor/jsonfield-validation
Author: Chris Lawlor
Author-email: lawlor.chris@gmail.com
Keywords: jsonfield_validation
Classifier: Development Status :: 2 - Pre-Alpha
Classifier: Intended Audience :: Developers
Classifier: Natural Language :: English
Classifier: Programming Language :: Python :: 3
Classifier: Programming Language :: Python :: 3.6
Classifier: Programming Language :: Python :: 3.7
Classifier: Programming Language :: Python :: 3.8
Classifier: Programming Language :: Python :: 3.9
Classifier: Programming Language :: Python :: 3.10
Classifier: Framework :: Django :: 1.11
Classifier: Framework :: Django :: 2.2
Classifier: Framework :: Django :: 3.2
Classifier: Framework :: Django :: 4.0
Requires-Python: >=3.6
License-File: LICENSE.txt
Requires-Dist: Django
Requires-Dist: jsonschema
